scattack/__init__.py
scattack/attackmeasure/__init__.py
scattack/attackmeasure/big_ttest.py
scattack/attackmeasure/cpa.py
scattack/attackmeasure/dpa.py
scattack/attackmeasure/modef_attack.py
scattack/attackmeasure/model_attack.py
scattack/attackmeasure/new_math.py
scattack/attackmeasure/t_testlll.py
scattack/attackmeasure/models/DES.py
scattack/attackmeasure/models/__init__.py
scattack/attackmeasure/models/base.py
scattack/attackmeasure/models/aes/__init__.py
scattack/attackmeasure/models/aes/funcs.py
scattack/attackmeasure/models/aes/key_schedule.py
scattack/attackmeasure/utils/__init__.py
scattack/attackmeasure/utils/aes_cipher.py
scattack/attackmeasure/utils/aes_tables.py
scattack/attackmeasure/utils/parameter.py
scattack/attackmeasure/utils/util.py
scattack/basetrace/__init__.py
scattack/basetrace/base.py
scattack/basetrace/data_resolve.py
scattack/basetrace/get_intermediate_value.py
scattack/basetrace/new_math.py
scattack/data_visualization/__init__.py
scattack/data_visualization/plt_ttest.py
scattack/data_visualization/test.py
scattack/leakage_testing/T_test.py
scattack/leakage_testing/__init__.py
scattack/leakage_testing/correlation_test.py
scattack/leakage_testing/snr.py
scattack/n_leakage_testing/__init__.py
scattack/n_leakage_testing/correlation.py
scattack/n_leakage_testing/pre_traces.py
scattack/n_leakage_testing/snr.py
scattack/n_leakage_testing/t-test.py
scattack/pretrace/__init__.py
scattack/pretrace/aligner.py
scattack/pretrace/base.py
scattack/pretrace/demo.py
scattack/pretrace/fft.py
scattack/pretrace/filter.py
scattack/pretrace/find_peaks.py
scattack/pretrace/moving_average.py
scattack/pretrace/new_math.py
scattack/pretrace/pre_traces.py
scattack/pretrace/principal_component_analysis.py
scattack/pretrace/sample.py
scattack/pretrace/to_one.py
scattack-0.0.1.dist-info/LICENSE
scattack-0.0.1.dist-info/METADATA
scattack-0.0.1.dist-info/WHEEL
scattack-0.0.1.dist-info/top_level.txt
scattack-0.0.1.dist-info/RECORD
