Metadata-Version: 2.1
Name: scattack
Version: 0.0.1
Summary: scattack
Home-page: UNKNOWN
Author: yangsu fanjie ji tianfu zhang weijia wang 
Author-email: 1152036203@qq.com
License: UNKNOWN
Platform: UNKNOWN
Classifier: Programming Language :: Python :: 3
Classifier: License :: OSI Approved :: MIT License
Classifier: Operating System :: OS Independent
Requires-Dist: pandas
Requires-Dist: matplotlib
Requires-Dist: numpy
Requires-Dist: scipy
Requires-Dist: pandas-profiling
Requires-Dist: folium
Requires-Dist: seaborn
